{"startDate": "20170601", "endDate": "20170630", "retCode": "000000", "retMsg": "get data from cache success", "sOperTime": "20170914143241", "curCuror": 1, "data": [{"remark": null, "infoType": "\u77ed\u4fe1", "commMode": "\u53d1\u9001", "busiName": "", "anotherNm": "13711746640", "startTime": "06-14 12:35:54", "commFee": "0.10", "commPlac": "\u5185\u5730", "meal": "\u52a8\u611f\u5730\u5e264G"}, {"remark": null, "infoType": "\u77ed\u4fe1", "commMode": "\u53d1\u9001", "busiName": "", "anotherNm": "13711746640", "startTime": "06-14 12:36:11", "commFee": "0.10", "commPlac": "\u5185\u5730", "meal": "\u52a8\u611f\u5730\u5e264G"}, {"remark": null, "infoType": "\u77ed\u4fe1", "commMode": "\u53d1\u9001", "busiName": "", "anotherNm": "18218670750", "startTime": "06-20 17:44:20", "commFee": "0.10", "commPlac": "\u5185\u5730", "meal": "\u52a8\u611f\u5730\u5e264G"}, {"remark": null, "infoType": "\u77ed\u4fe1", "commMode": "\u53d1\u9001", "busiName": "", "anotherNm": "18218670750", "startTime": "06-20 17:44:21", "commFee": "0.10", "commPlac": "\u5185\u5730", "meal": "\u52a8\u611f\u5730\u5e264G"}], "totalNum": 4}