{"startDate": "20170601", "endDate": "20170630", "retCode": "000000", "retMsg": "get data from cache success", "sOperTime": "20170914154130", "curCuror": 1, "data": [{"commType": "\u9ad8\u6e05\u8bed\u97f3\u56fd\u5185\u957f\u9014", "remark": null, "commPlac": "\u5e7f\u5dde", "mealFavorable": "\u795e\u5dde\u884c\u8f7b\u677e\u53610\u6708\u79df\u5957\u9910(\u6c55\u5934)", "commMode": "\u88ab\u53eb", "commTime": "05\u520635\u79d2", "anotherNm": "671738", "startTime": "06-08 17:45:22", "commFee": "0.00"}, {"commType": "\u9ad8\u6e05\u8bed\u97f3\u56fd\u5185\u957f\u9014", "remark": null, "commPlac": "\u5e7f\u5dde", "mealFavorable": "\u795e\u5dde\u884c\u8f7b\u677e\u53610\u6708\u79df\u5957\u9910(\u6c55\u5934)", "commMode": "\u88ab\u53eb", "commTime": "02\u520649\u79d2", "anotherNm": "671738", "startTime": "06-13 11:52:19", "commFee": "0.00"}, {"commType": "\u9ad8\u6e05\u8bed\u97f3\u56fd\u5185\u957f\u9014", "remark": null, "commPlac": "\u5e7f\u5dde", "mealFavorable": "\u795e\u5dde\u884c\u8f7b\u677e\u53610\u6708\u79df\u5957\u9910(\u6c55\u5934)", "commMode": "\u88ab\u53eb", "commTime": "38\u79d2", "anotherNm": "671738", "startTime": "06-13 16:07:48", "commFee": "0.00"}, {"commType": "\u9ad8\u6e05\u8bed\u97f3\u56fd\u5185\u957f\u9014", "remark": null, "commPlac": "\u5e7f\u5dde", "mealFavorable": "\u795e\u5dde\u884c\u8f7b\u677e\u53610\u6708\u79df\u5957\u9910(\u6c55\u5934)", "commMode": "\u88ab\u53eb", "commTime": "32\u79d2", "anotherNm": "662018", "startTime": "06-13 20:34:06", "commFee": "0.00"}, {"commType": "\u9ad8\u6e05\u8bed\u97f3\u56fd\u5185\u957f\u9014", "remark": null, "commPlac": "\u5e7f\u5dde", "mealFavorable": "\u795e\u5dde\u884c\u8f7b\u677e\u53610\u6708\u79df\u5957\u9910(\u6c55\u5934)", "commMode": "\u88ab\u53eb", "commTime": "47\u79d2", "anotherNm": "662018", "startTime": "06-13 20:55:29", "commFee": "0.00"}, {"commType": "\u9ad8\u6e05\u8bed\u97f3\u56fd\u5185\u957f\u9014", "remark": null, "commPlac": "\u5e7f\u5dde", "mealFavorable": "\u795e\u5dde\u884c\u8f7b\u677e\u53610\u6708\u79df\u5957\u9910(\u6c55\u5934)", "commMode": "\u88ab\u53eb", "commTime": "01\u520601\u79d2", "anotherNm": "662018", "startTime": "06-13 20:57:34", "commFee": "0.00"}, {"commType": "\u56fd\u5185\u957f\u9014", "remark": null, "commPlac": "\u5e7f\u5dde", "mealFavorable": "\u795e\u5dde\u884c\u8f7b\u677e\u5361", "commMode": "\u4e3b\u53eb", "commTime": "01\u520602\u79d2", "anotherNm": "671738", "startTime": "06-13 21:04:52", "commFee": "0.98"}, {"commType": "\u9ad8\u6e05\u8bed\u97f3\u56fd\u5185\u957f\u9014", "remark": null, "commPlac": "\u5e7f\u5dde", "mealFavorable": "\u795e\u5dde\u884c\u8f7b\u677e\u53610\u6708\u79df\u5957\u9910(\u6c55\u5934)", "commMode": "\u88ab\u53eb", "commTime": "24\u79d2", "anotherNm": "662018", "startTime": "06-14 06:33:27", "commFee": "0.00"}, {"commType": "\u56fd\u5185\u957f\u9014", "remark": null, "commPlac": "\u5e7f\u5dde", "mealFavorable": "\u795e\u5dde\u884c\u8f7b\u677e\u5361", "commMode": "\u4e3b\u53eb", "commTime": "20\u79d2", "anotherNm": "662018", "startTime": "06-14 07:00:27", "commFee": "0.49"}, {"commType": "\u9ad8\u6e05\u8bed\u97f3\u56fd\u5185\u957f\u9014", "remark": null, "commPlac": "\u5e7f\u5dde", "mealFavorable": "\u795e\u5dde\u884c\u8f7b\u677e\u53610\u6708\u79df\u5957\u9910(\u6c55\u5934)", "commMode": "\u88ab\u53eb", "commTime": "27\u79d2", "anotherNm": "662018", "startTime": "06-14 07:30:08", "commFee": "0.00"}, {"commType": "\u9ad8\u6e05\u8bed\u97f3\u56fd\u5185\u957f\u9014", "remark": null, "commPlac": "\u5e7f\u5dde", "mealFavorable": "\u795e\u5dde\u884c\u8f7b\u677e\u53610\u6708\u79df\u5957\u9910(\u6c55\u5934)", "commMode": "\u88ab\u53eb", "commTime": "15\u79d2", "anotherNm": "662018", "startTime": "06-14 07:36:13", "commFee": "0.00"}, {"commType": "\u9ad8\u6e05\u8bed\u97f3\u56fd\u5185\u957f\u9014", "remark": null, "commPlac": "\u5e7f\u5dde", "mealFavorable": "\u795e\u5dde\u884c\u8f7b\u677e\u53610\u6708\u79df\u5957\u9910(\u6c55\u5934)", "commMode": "\u88ab\u53eb", "commTime": "11\u79d2", "anotherNm": "662018", "startTime": "06-14 07:46:49", "commFee": "0.00"}, {"commType": "\u9ad8\u6e05\u8bed\u97f3\u56fd\u5185\u957f\u9014", "remark": null, "commPlac": "\u5e7f\u5dde", "mealFavorable": "\u795e\u5dde\u884c\u8f7b\u677e\u53610\u6708\u79df\u5957\u9910(\u6c55\u5934)", "commMode": "\u88ab\u53eb", "commTime": "16\u79d2", "anotherNm": "662018", "startTime": "06-14 08:12:04", "commFee": "0.00"}, {"commType": "\u9ad8\u6e05\u8bed\u97f3\u56fd\u5185\u957f\u9014", "remark": null, "commPlac": "\u5e7f\u5dde", "mealFavorable": "\u795e\u5dde\u884c\u8f7b\u677e\u53610\u6708\u79df\u5957\u9910(\u6c55\u5934)", "commMode": "\u88ab\u53eb", "commTime": "24\u79d2", "anotherNm": "662018", "startTime": "06-14 08:35:19", "commFee": "0.00"}, {"commType": "\u9ad8\u6e05\u8bed\u97f3\u672c\u5730", "remark": null, "commPlac": "\u5e7f\u5dde", "mealFavorable": "\u795e\u5dde\u884c\u8f7b\u677e\u53610\u6708\u79df\u5957\u9910(\u6c55\u5934)", "commMode": "\u88ab\u53eb", "commTime": "25\u79d2", "anotherNm": "13570708060", "startTime": "06-14 09:45:51", "commFee": "0.00"}, {"commType": "\u56fd\u5185\u957f\u9014", "remark": null, "commPlac": "\u5e7f\u5dde", "mealFavorable": "\u795e\u5dde\u884c\u8f7b\u677e\u5361", "commMode": "\u4e3b\u53eb", "commTime": "48\u79d2", "anotherNm": "671738", "startTime": "06-14 11:56:06", "commFee": "0.49"}, {"commType": "\u56fd\u5185\u957f\u9014", "remark": null, "commPlac": "\u5e7f\u5dde", "mealFavorable": "\u795e\u5dde\u884c\u8f7b\u677e\u5361", "commMode": "\u4e3b\u53eb", "commTime": "23\u79d2", "anotherNm": "662018", "startTime": "06-14 14:58:55", "commFee": "0.49"}, {"commType": "\u9ad8\u6e05\u8bed\u97f3\u56fd\u5185\u957f\u9014", "remark": null, "commPlac": "\u5e7f\u5dde", "mealFavorable": "\u795e\u5dde\u884c\u8f7b\u677e\u53610\u6708\u79df\u5957\u9910(\u6c55\u5934)", "commMode": "\u88ab\u53eb", "commTime": "28\u79d2", "anotherNm": "662018", "startTime": "06-14 16:13:43", "commFee": "0.00"}, {"commType": "\u9ad8\u6e05\u8bed\u97f3\u56fd\u5185\u957f\u9014", "remark": null, "commPlac": "\u5e7f\u5dde", "mealFavorable": "\u795e\u5dde\u884c\u8f7b\u677e\u53610\u6708\u79df\u5957\u9910(\u6c55\u5934)", "commMode": "\u88ab\u53eb", "commTime": "01\u520658\u79d2", "anotherNm": "662018", "startTime": "06-15 13:00:20", "commFee": "0.00"}, {"commType": "\u9ad8\u6e05\u8bed\u97f3\u56fd\u5185\u957f\u9014", "remark": null, "commPlac": "\u5e7f\u5dde", "mealFavorable": "\u795e\u5dde\u884c\u8f7b\u677e\u53610\u6708\u79df\u5957\u9910(\u6c55\u5934)", "commMode": "\u88ab\u53eb", "commTime": "04\u520641\u79d2", "anotherNm": "662018", "startTime": "06-19 10:24:38", "commFee": "0.00"}, {"commType": "\u9ad8\u6e05\u8bed\u97f3\u56fd\u5185\u957f\u9014", "remark": null, "commPlac": "\u5e7f\u5dde", "mealFavorable": "\u795e\u5dde\u884c\u8f7b\u677e\u53610\u6708\u79df\u5957\u9910(\u6c55\u5934)", "commMode": "\u88ab\u53eb", "commTime": "03\u520646\u79d2", "anotherNm": "662018", "startTime": "06-19 10:34:53", "commFee": "0.00"}, {"commType": "\u9ad8\u6e05\u8bed\u97f3\u56fd\u5185\u957f\u9014", "remark": null, "commPlac": "\u5e7f\u5dde", "mealFavorable": "\u795e\u5dde\u884c\u8f7b\u677e\u53610\u6708\u79df\u5957\u9910(\u6c55\u5934)", "commMode": "\u88ab\u53eb", "commTime": "03\u79d2", "anotherNm": "662018", "startTime": "06-19 18:07:52", "commFee": "0.00"}, {"commType": "\u9ad8\u6e05\u8bed\u97f3\u56fd\u5185\u957f\u9014", "remark": null, "commPlac": "\u5e7f\u5dde", "mealFavorable": "\u795e\u5dde\u884c\u8f7b\u677e\u53610\u6708\u79df\u5957\u9910(\u6c55\u5934)", "commMode": "\u88ab\u53eb", "commTime": "21\u79d2", "anotherNm": "662018", "startTime": "06-19 18:08:21", "commFee": "0.00"}, {"commType": "\u9ad8\u6e05\u8bed\u97f3\u672c\u5730", "remark": null, "commPlac": "\u5e7f\u5dde", "mealFavorable": "\u795e\u5dde\u884c\u8f7b\u677e\u53610\u6708\u79df\u5957\u9910(\u6c55\u5934)", "commMode": "\u88ab\u53eb", "commTime": "08\u79d2", "anotherNm": "18819477281", "startTime": "06-24 15:16:20", "commFee": "0.00"}, {"commType": "\u9ad8\u6e05\u8bed\u97f3\u56fd\u5185\u957f\u9014", "remark": null, "commPlac": "\u5e7f\u5dde", "mealFavorable": "\u795e\u5dde\u884c\u8f7b\u677e\u53610\u6708\u79df\u5957\u9910(\u6c55\u5934)", "commMode": "\u88ab\u53eb", "commTime": "05\u520638\u79d2", "anotherNm": "662018", "startTime": "06-28 10:04:00", "commFee": "0.00"}, {"commType": "\u9ad8\u6e05\u8bed\u97f3\u56fd\u5185\u957f\u9014", "remark": null, "commPlac": "\u5e7f\u5dde", "mealFavorable": "\u795e\u5dde\u884c\u8f7b\u677e\u53610\u6708\u79df\u5957\u9910(\u6c55\u5934)", "commMode": "\u88ab\u53eb", "commTime": "05\u520607\u79d2", "anotherNm": "662018", "startTime": "06-28 10:13:18", "commFee": "0.00"}], "totalNum": 26}